{
    "distance_from_centre_in_km": 71.0,
    "bedrooms": 48.0,
    "accommodates": 47.0,
    "host_listings_count": 46.0,
    "bathrooms": 40.0,
    "availability_365": 33.0,
    "latitude": 30.0,
    "#_listings_in_neighbourhood": 30.0,
    "component_53": 29.0,
    "component_54": 27.0,
    "longitude": 25.0,
    "review_scores_rating": 24.0,
    "reviews_per_month": 24.0,
    "component_85": 24.0,
    "availability_90": 21.0,
    "component_84": 21.0,
    "availability_60": 20.0,
    "component_69": 19.0,
    "minimum_nights": 18.0,
    "host_response_rate": 15.0,
    "component_95": 15.0,
    "component_87": 14.0,
    "component_51": 13.0,
    "component_55": 13.0,
    "component_75": 13.0,
    "number_of_reviews": 12.0,
    "component_29": 12.0,
    "component_89": 12.0,
    "component_94": 12.0,
    "component_96": 12.0,
    "review_scores_cleanliness": 11.0,
    "host_identity_verified_f": 11.0,
    "component_62": 11.0,
    "component_65": 11.0,
    "component_83": 11.0,
    "component_91": 11.0,
    "component_98": 11.0,
    "component_4": 10.0,
    "component_45": 10.0,
    "component_58": 10.0,
    "component_2": 9.0,
    "component_6": 9.0,
    "component_32": 9.0,
    "component_52": 9.0,
    "component_59": 9.0,
    "component_63": 9.0,
    "component_68": 9.0,
    "component_97": 9.0,
    "babysitter recommendations": 8.0,
    "dishwasher": 8.0,
    "full kitchen": 8.0,
    "tv": 8.0,
    "component_17": 8.0,
    "component_82": 8.0,
    "availability_30": 7.0,
    "number_of_reviews_ltm": 7.0,
    "review_scores_value": 7.0,
    "air conditioning": 7.0,
    "elevator": 7.0,
    "essentials": 7.0,
    "gym": 7.0,
    "indoor fireplace": 7.0,
    "component_1": 7.0,
    "component_3": 7.0,
    "component_5": 7.0,
    "component_9": 7.0,
    "component_33": 7.0,
    "component_66": 7.0,
    "component_77": 7.0,
    "component_79": 7.0,
    "beds": 6.0,
    "work_email": 6.0,
    "neighbourhood_cleansed_Southwark": 6.0,
    "component_11": 6.0,
    "component_16": 6.0,
    "component_30": 6.0,
    "component_38": 6.0,
    "component_44": 6.0,
    "component_56": 6.0,
    "component_60": 6.0,
    "component_78": 6.0,
    "component_88": 6.0,
    "component_93": 6.0,
    "review_scores_location": 5.0,
    "cable tv": 5.0,
    "free street parking": 5.0,
    "lockbox": 5.0,
    "private living room": 5.0,
    "neighbourhood_cleansed_City of London": 5.0,
    "neighbourhood_cleansed_Richmond upon Thames": 5.0,
    "component_15": 5.0,
    "component_23": 5.0,
    "component_27": 5.0,
    "component_64": 5.0,
    "component_67": 5.0,
    "component_73": 5.0,
    "component_92": 5.0,
    "component_99": 5.0,
    "review_scores_checkin": 4.0,
    "coffee maker": 4.0,
    "shampoo": 4.0,
    "smoking allowed": 4.0,
    "identity_manual": 4.0,
    "neighbourhood_cleansed_Camden": 4.0,
    "component_7": 4.0,
    "component_19": 4.0,
    "component_21": 4.0,
    "component_47": 4.0,
    "component_49": 4.0,
    "component_50": 4.0,
    "component_70": 4.0,
    "component_72": 4.0,
    "component_80": 4.0,
    "component_86": 4.0,
    "dishes and silverware": 3.0,
    "dryer": 3.0,
    "pool": 3.0,
    "room darkening shades": 3.0,
    "smart lock": 3.0,
    "reviews": 3.0,
    "component_18": 3.0,
    "component_28": 3.0,
    "component_41": 3.0,
    "component_42": 3.0,
    "component_61": 3.0,
    "component_76": 3.0,
    "component_90": 3.0,
    "children s books and toys": 2.0,
    "extra pillows and blankets": 2.0,
    "heated floors": 2.0,
    "phone": 2.0,
    "neighbourhood_cleansed_Barnet": 2.0,
    "component_8": 2.0,
    "component_12": 2.0,
    "component_13": 2.0,
    "component_24": 2.0,
    "component_25": 2.0,
    "component_26": 2.0,
    "component_31": 2.0,
    "component_35": 2.0,
    "component_46": 2.0,
    "component_100": 2.0,
    "review_scores_accuracy": 1.0,
    "bath towel": 1.0,
    "bathroom essentials": 1.0,
    "breakfast": 1.0,
    "building staff": 1.0,
    "carbon monoxide detector": 1.0,
    "cooking basics": 1.0,
    "ethernet connection": 1.0,
    "heating": 1.0,
    "hot water": 1.0,
    "hour check in": 1.0,
    "iron": 1.0,
    "kitchen": 1.0,
    "oven": 1.0,
    "safety card": 1.0,
    "smoke detector": 1.0,
    "email": 1.0,
    "facebook": 1.0,
    "google": 1.0,
    "neighbourhood_cleansed_Islington": 1.0,
    "instant_bookable_f": 1.0,
    "host_response_time_within an hour": 1.0,
    "component_10": 1.0,
    "component_22": 1.0,
    "component_34": 1.0,
    "component_36": 1.0,
    "component_39": 1.0,
    "component_57": 1.0,
    "component_71": 1.0,
    "component_74": 1.0,
    "component_81": 1.0
}